Products.ZCatalog-7.2.1-py3.12-nspkg.pth
Products/PluginIndexes/__init__.py
Products/PluginIndexes/cache.py
Products/PluginIndexes/interfaces.py
Products/PluginIndexes/unindex.py
Products/PluginIndexes/util.py
Products/PluginIndexes/BooleanIndex/BooleanIndex.py
Products/PluginIndexes/BooleanIndex/__init__.py
Products/PluginIndexes/BooleanIndex/tests.py
Products/PluginIndexes/BooleanIndex/dtml/addBooleanIndex.dtml
Products/PluginIndexes/BooleanIndex/dtml/manageBooleanIndex.dtml
Products/PluginIndexes/CompositeIndex/CompositeIndex.py
Products/PluginIndexes/CompositeIndex/README.txt
Products/PluginIndexes/CompositeIndex/__init__.py
Products/PluginIndexes/CompositeIndex/dtml/addCompositeIndex.dtml
Products/PluginIndexes/CompositeIndex/dtml/browseIndex.dtml
Products/PluginIndexes/CompositeIndex/dtml/manageCompositeIndex.dtml
Products/PluginIndexes/CompositeIndex/tests/__init__.py
Products/PluginIndexes/CompositeIndex/tests/testCompositeIndex.py
Products/PluginIndexes/DateIndex/DateIndex.py
Products/PluginIndexes/DateIndex/README.txt
Products/PluginIndexes/DateIndex/__init__.py
Products/PluginIndexes/DateIndex/tests.py
Products/PluginIndexes/DateIndex/dtml/addDateIndex.dtml
Products/PluginIndexes/DateIndex/dtml/manageDateIndex.dtml
Products/PluginIndexes/DateRangeIndex/DateRangeIndex.py
Products/PluginIndexes/DateRangeIndex/README.txt
Products/PluginIndexes/DateRangeIndex/__init__.py
Products/PluginIndexes/DateRangeIndex/tests.py
Products/PluginIndexes/DateRangeIndex/dtml/addDateRangeIndex.dtml
Products/PluginIndexes/DateRangeIndex/dtml/manageDateRangeIndex.dtml
Products/PluginIndexes/FieldIndex/FieldIndex.py
Products/PluginIndexes/FieldIndex/__init__.py
Products/PluginIndexes/FieldIndex/tests.py
Products/PluginIndexes/FieldIndex/dtml/addFieldIndex.dtml
Products/PluginIndexes/FieldIndex/dtml/manageFieldIndex.dtml
Products/PluginIndexes/KeywordIndex/KeywordIndex.py
Products/PluginIndexes/KeywordIndex/__init__.py
Products/PluginIndexes/KeywordIndex/tests.py
products_zcatalog-7.2.1.dist-info/LICENSE.txt
products_zcatalog-7.2.1.dist-info/METADATA
products_zcatalog-7.2.1.dist-info/WHEEL
products_zcatalog-7.2.1.dist-info/namespace_packages.txt
products_zcatalog-7.2.1.dist-info/top_level.txt
products_zcatalog-7.2.1.dist-info/RECORD
