Metadata-Version: 2.2
Name: Products.ZCatalog
Version: 7.2.1
Summary: Zope's indexing and search solution.
Home-page: https://github.com/zopefoundation/Products.ZCatalog
Author: Zope Foundation and Contributors
Author-email: zope-dev@zope.dev
License: ZPL-2.1
Project-URL: Issue Tracker, https://github.com/zopefoundation/Products.ZCatalog/issues
Project-URL: Sources, https://github.com/zopefoundation/Products.ZCatalog
Keywords: Zope catalog index search data
Classifier: Development Status :: 6 - Mature
Classifier: Environment :: Web Environment
Classifier: Framework :: Zope
Classifier: Framework :: Zope :: 5
Classifier: License :: OSI Approved :: Zope Public License
Classifier: Operating System :: OS Independent
Classifier: Programming Language :: Python
Classifier: Programming Language :: Python :: 3
Classifier: Programming Language :: Python :: 3.9
Classifier: Programming Language :: Python :: 3.10
Classifier: Programming Language :: Python :: 3.11
Classifier: Programming Language :: Python :: 3.12
Classifier: Programming Language :: Python :: 3.13
Classifier: Programming Language :: Python :: Implementation :: CPython
Classifier: Topic :: Internet :: WWW/HTTP :: Indexing/Search
Requires-Python: >=3.9
License-File: LICENSE.txt
Requires-Dist: setuptools
Requires-Dist: AccessControl>=4.0a4
Requires-Dist: Acquisition
Requires-Dist: BTrees
Requires-Dist: DateTime
Requires-Dist: DocumentTemplate
Requires-Dist: ExtensionClass
Requires-Dist: Missing
Requires-Dist: Persistence
Requires-Dist: Record
Requires-Dist: RestrictedPython>=5.1
Requires-Dist: zExceptions
Requires-Dist: ZODB
Requires-Dist: Zope>=4
Requires-Dist: zope.deferredimport
Requires-Dist: zope.dottedname
Requires-Dist: zope.globalrequest
Requires-Dist: zope.interface
Requires-Dist: zope.schema
Requires-Dist: zope.testing
Dynamic: author
Dynamic: author-email
Dynamic: classifier
Dynamic: description
Dynamic: home-page
Dynamic: keywords
Dynamic: license
Dynamic: project-url
Dynamic: requires-dist
Dynamic: requires-python
Dynamic: summary
